{
  "schemaVersion": "echo.content_graph.export_plan.v1",
  "moduleId": "echoadaptercore",
  "runtimeTarget": "neoforge",
  "mappings": [
    {
      "nodeId": "echoadaptercore:capability/runtime_bridge",
      "runtimeId": "echoadaptercore:capability/runtime_bridge",
      "kind": "CAPABILITY",
      "adapter": "adaptercore.neoforge.capability"
    },
    {
      "nodeId": "echoadaptercore:service/runtime_bridge",
      "runtimeId": "echoadaptercore:service/runtime_bridge",
      "kind": "SERVICE",
      "adapter": "adaptercore.neoforge.service"
    }
  ]
}
